tf_gnns/__init__.py
tf_gnns/graphnet_utils.py
tf_gnns/tfgnns_datastructures.py
tf_gnns/utils.py
tf_gnns/utils_train.py
tf_gnns/assets/html_css/accordion.js
tf_gnns/assets/html_css/pretty_print_accordion.css
tf_gnns/lib/__init__.py
tf_gnns/lib/gt_ops.py
tf_gnns/models/__init__.py
tf_gnns/models/graphnet.py
tf_gnns-0.1.8.dist-info/LICENSE
tf_gnns-0.1.8.dist-info/METADATA
tf_gnns-0.1.8.dist-info/WHEEL
tf_gnns-0.1.8.dist-info/top_level.txt
tf_gnns-0.1.8.dist-info/RECORD
