Metadata-Version: 2.1
Name: tf-gnns
Version: 0.1.8
Summary: A hackable graphnets library for tensorflow-keras.
Home-page: https://github.com/mylonasc/tf_gnns.git
Author: Charilaos Mylonas
Author-email: mylonas.charilaos@gmail.com
License: UNKNOWN
Platform: UNKNOWN
Classifier: Programming Language :: Python :: 3
Classifier: License :: OSI Approved :: Apache Software License
Classifier: Operating System :: OS Independent
Requires-Python: >=3.6
License-File: LICENSE
